autoinstallcmtpack-1.1.0.data/data/LICENSE
configCmtPack/CheckBOSS.py
configCmtPack/GitSvc.py
configCmtPack/PackageSvc.py
configCmtPack/ProcessRequire.py
configCmtPack/RepoSet.py
configCmtPack/__init__.py
configCmtPack/main.py
configCmtPack/util.py
autoinstallcmtpack-1.1.0.dist-info/LICENSE
autoinstallcmtpack-1.1.0.dist-info/METADATA
autoinstallcmtpack-1.1.0.dist-info/WHEEL
autoinstallcmtpack-1.1.0.dist-info/entry_points.txt
autoinstallcmtpack-1.1.0.dist-info/top_level.txt
autoinstallcmtpack-1.1.0.dist-info/RECORD
