Metadata-Version: 2.1
Name: autoinstallcmtpack
Version: 1.1.0
Summary: Auto instal the package from the requirement
Home-page: UNKNOWN
Author: Xin-Xin Ma
Author-email: UNKNOWN
License: GPL
Platform: UNKNOWN
